hapla/__init__.py
hapla/admix.py
hapla/admix_cy.cpython-311-darwin.so
hapla/cluster.py
hapla/cluster_cy.cpython-311-darwin.so
hapla/fatash.py
hapla/fatash_cy.cpython-311-darwin.so
hapla/functions.py
hapla/main.py
hapla/memory_cy.cpython-311-darwin.so
hapla/predict.py
hapla/reader_cy.cpython-311-darwin.so
hapla/shared_cy.cpython-311-darwin.so
hapla/struct.py
hapla-0.13.dist-info/LICENSE
hapla-0.13.dist-info/METADATA
hapla-0.13.dist-info/WHEEL
hapla-0.13.dist-info/entry_points.txt
hapla-0.13.dist-info/top_level.txt
hapla-0.13.dist-info/RECORD
