Metadata-Version: 2.1
Name: hapla
Version: 0.13
Summary: Framework for haplotype clustering in phased genotype data
Home-page: https://github.com/Rosemeis/hapla
Author: Jonas Meisner
Author-email: meisnerucph@gmail.com
Classifier: Programming Language :: Python :: 3
Classifier: License :: OSI Approved :: GNU General Public License v3 (GPLv3)
Classifier: Operating System :: OS Independent
Classifier: Development Status :: 4 - Beta
Requires-Python: >=3.10
License-File: LICENSE
Requires-Dist: cython >3.0.0
Requires-Dist: cyvcf2 >=0.31.0
Requires-Dist: numpy >2.0.0
